aioworkers_loki/__init__.py
aioworkers_loki/config.ini
aioworkers_loki-0.1.0b4.dist-info/LICENSE
aioworkers_loki-0.1.0b4.dist-info/WHEEL
aioworkers_loki-0.1.0b4.dist-info/METADATA
aioworkers_loki-0.1.0b4.dist-info/RECORD
