Metadata-Version: 2.1
Name: aioworkers-loki
Version: 0.1.0b4
Summary: 
Home-page: https://github.com/aioworkers/aioworkers-loki
License: Apache Software License 2.0
Author: Alexander Malev
Author-email: malev@somedev.ru
Requires-Python: >=3.6,<4.0
Classifier: Development Status :: 2 - Pre-Alpha
Classifier: Framework :: AsyncIO
Classifier: Intended Audience :: Developers
Classifier: License :: OSI Approved :: Apache Software License
Classifier: License :: Other/Proprietary License
Classifier: Programming Language :: Python :: 3
Classifier: Programming Language :: Python :: 3 :: Only
Classifier: Programming Language :: Python :: 3.10
Classifier: Programming Language :: Python :: 3.6
Classifier: Programming Language :: Python :: 3.7
Classifier: Programming Language :: Python :: 3.8
Classifier: Programming Language :: Python :: 3.9
Requires-Dist: aioworkers (>=0.18)
Requires-Dist: python-logging-loki (>=0.3.1,<0.4.0)
Project-URL: Repository, https://github.com/aioworkers/aioworkers-loki
